dokusan/__init__.py
dokusan/boards.py
dokusan/exceptions.py
dokusan/generators.py
dokusan/py.typed
dokusan/renderers.py
dokusan/solvers.py
dokusan/stats.py
dokusan/techniques.py
dokusan-0.1.0a6.dist-info/LICENSE
dokusan-0.1.0a6.dist-info/WHEEL
dokusan-0.1.0a6.dist-info/METADATA
dokusan-0.1.0a6.dist-info/RECORD
