Metadata-Version: 2.1
Name: dokusan
Version: 0.1.0a6
Summary: Sudoku generator and solver with a step-by-step guidance
License: GPL-3.0
Keywords: sudoku,sudoku-solver,sudoku-generator,solver,generator
Author: Aleksei Maslakov
Author-email: lesha.maslakov@gmail.com
Requires-Python: >=3.8,<4.0
Classifier: Development Status :: 3 - Alpha
Classifier: License :: OSI Approved :: GNU General Public License v3 (GPLv3)
Classifier: Operating System :: OS Independent
Classifier: Programming Language :: Python :: 3
Classifier: Programming Language :: Python :: 3.8
Classifier: Topic :: Games/Entertainment :: Puzzle Games
Classifier: Typing :: Typed
